{
  "err_wrongCredentials": "Nombre de usuario o contraseña equivocada, por favor intente otra vez",
  "button_no": "No",
  "button_yes": "Sí",
  "button_login": "ACCESO",
  "menu_incident": "Agregar incidente",
  "button_logout": "Finalizar",
  "menu_fuel": "Agregue combustible",
  "menu_disposal": "Agregar disposición",
  "button_cancel": "Cancelar",
  "toast_failedNetworkRequest": "Su solicitud ha fallado debido a la falla de la red, intente nuevamente",
  "title_connectionIssue": "Conexión de espera",
  "alert_connectionWarning": "Se requiere conexión a Internet para acceder al servidor. Asegúrese de tener acceso a Internet. Código de emisión de \n: {issueCode}",
  "title_signTheTask": "Firma",
  "toast_answerQuestions": "¡Por favor responda todas las preguntas!",
  "txt_incidentSent": "Tu incidente ha sido enviado",
  "txt_incidentSentFail": "Su incidente no pudo enviar, intente de nuevo",
  "title_warning": "Advertencia",
  "txt_enableLocation": "Su ubicación GPS es deficiente, habilite la ubicación y asegúrese de posicionarlo",
  "alert_noOperation": "No hay operación asignada para su aplicación \n inicio de sesión después de cerrar esta ventana emergente",
  "alert_failRestartNeeded": "Nos enfrentamos a un problema que requiere el inicio de sesión. Código: {error}",
  "txt_doYouLogout": "¿Quieres cerrar sesión?",
  "alert_networkFailure": "Algo se equivoca en nuestra conexión de red, intente nuevamente",
  "label_amount": "Cantidad",
  "txt_entityName": "Nombre de la entidad",
  "txt_servicePointName": "Nombre del punto de servicio",
  "txt_address": "DIRECCIÓN",
  "txt_createDate": "Fecha de Creación",
  "txt_taskId": "ID de tarea",
  "txt_jobId": "Identificación del trabajo",
  "txt_dueDate": "Fecha de vencimiento",
  "txt_status": "Estado",
  "txt_assignDate": "Fecha de asignación",
  "txt_lastUpdated": "Última actualización",
  "txt_assignerName": "Nombre del cesionador",
  "txt_creatorName": "Nombre del creador",
  "txt_actualQuantity": "Cantidad actual",
  "txt_description": "Descripción",
  "txt_item": "Artículo",
  "txt_wasteItems": "Artículos de servicio",
  "alert_taskLoadFail": "No podríamos cargar esta tarea, estamos trabajando en ello.",
  "txt_actualPlannedQ": "Real / planeado P.",
  "txt_actualPlannedA": "Real / planeado A.",
  "label_operation": "Operación",
  "title_noGpsData": "Esperando datos del GPS",
  "alert_enableGPS": "No se puede conectar a los servicios de ubicación en este momento, intentando de nuevo ...",
  "btn_startRoute": "Ruta de inicio",
  "btn_endRoute": "Ruta de finalización",
  "menu_break": "Tomar un descanso",
  "txt_today": "Hoy",
  "txt_now": "En este momento",
  "txt_yesterday": "Ayer",
  "toast_breakTimeIsOut": "Su tiempo de descanso permitido está fuera, ya no puedes comenzar a romper.",
  "txt_comment": "Nota",
  "btn_call": "Llamar al número",
  "txt_actualQ": "Cantidad actual",
  "txt_plannedQ": "Cantidad planificada",
  "txt_actualA": "Monto real",
  "txt_plannedA": "Cantidad planificada",
  "btn_addSignature": "Agregar firma",
  "txt_transitionTo": "Transición a {transitionCategoryName}",
  "alert_transitionFailure": "Algo salió mal durante la completación de su transición, intente nuevamente",
  "alert_selectMandatoryAssetBeforeComplete": "Por favor, seleccione todos los activos obligatorios antes de que puedan completar la transición.",
  "alert_fillAllRequiredDataBeforeComplete": "Por favor, complete todos los datos requeridos antes de que puedan completar la transición.",
  "alert_pickAllRequiredPictureBeforeComplete": "Por favor, elija toda la imagen requerida antes de que pueda completar la transición.",
  "alert_signAllRequiredSignatureBeforeComplete": "Por favor, firme toda la firma requerida antes de que pueda completar la transición.",
  "alert_fillAllRequiredItemBeforeComplete": "Por favor, complete todos los datos del elemento requeridos antes de que puedan completar la transición.",
  "alert_transitionCompletedSuccessfully": "La transición ha enviado con éxito",
  "err_rfidReaderError": "No se encuentra la etiqueta RFID, intente nuevamente.",
  "err_assetAttachNetworkIssue": "Desafortunadamente, este activo no se puede conectar a la ruta, consulte su conexión de red e intente nuevamente.",
  "txt_attachedAssetSuccessfully": "Activo adjunto a la ruta con éxito.",
  "txt_detachedAssetSuccessfully": "Activo separado de la ruta con éxito.",
  "err_assetDetachNetworkIssue": "Desafortunadamente, este activo no se puede separar de la ruta, consulte su conexión de red e intente nuevamente.",
  "err_internalError": "Se produjo un error interno \n, comuníquese con el administrador",
  "title_activityRecognitionNeeded": "Se necesita permiso de reconocimiento de actividad",
  "txt_activityRecognitionNeeded": "Para poder utilizar el servicio de seguimiento, necesitamos acceder al permiso de reconocimiento de actividad para la optimización de la batería. \n \n Estos datos solo se utilizarán para los servicios de ubicación hasta el inicio de sesión.",
  "title_appUpdateRequired": "Actualización requerida",
  "btn_appUpdateRequired": "Actualizar",
  "txt_offlineStatusName": "{status_name} (esperando)",
  "menu_scanQrCode": "Escanear código QR",
  "err_gpsPermissionRequiredForLogin": "Debe permitir el permiso GPS para continuar la operación",
  "btn_allow": "Permitir",
  "btn_deny": "Denegar",
  "err_activityRecognitionRequiredForLogin": "Debe permitir que el reconocimiento de actividad continúe operando",
  "hint_enterPassword": "Introducir la contraseña",
  "hint_enterUserName": "Introduzca su nombre de usuario",
  "hint_enterDriverId": "Ingrese la identificación del controlador",
  "tab_userName": "Nombre de usuario",
  "tab_driverId": "ID de controlador",
  "txt_route": "Ruta",
  "err_tasksNotLoaded": "Espere hasta la carga de un conjunto de datos completo",
  "err_wrongCredentialsForDriver": "ID de conductor incorrecto, intente nuevamente",
  "title_privacyPolicy": "política de privacidad",
  "title_yourRoutes": "Tus rutas",
  "empty_title_noRouteAssigned": "No hay ruta asignada",
  "empty_desc_noRouteAssigned": "Desafortunadamente, no hay una ruta activa asignada a usted. Por favor, hable con su supervisor.",
  "label_starts": "Empieza",
  "label_ends": "Fines",
  "label_tasks": "Tareas",
  "txt_mapDefaultView": "Vista predeterminada",
  "txt_mapSatelliteView": "Vista satelital",
  "title_settings": "Ajustes",
  "label_mapAndInterface": "Mapa e interfaz",
  "label_mapView": "Vista del mapa",
  "label_voiceGuidance": "Guía de voz",
  "label_instantTrafficInfo": "Información de tráfico instantáneo",
  "label_showDisposalfuelPoints": "Mostrar puntos de eliminación/combustible",
  "title_preRouteQuestions": "Preguntas previas a la ruta",
  "label_vehicleReadings": "Lectura de vehículos",
  "label_qhse": "QHSE",
  "btn_back": "Atrás",
  "btn_next": "Próximo",
  "err_fillAllFields": "Se requiere completar todos los campos.",
  "label_details": "Detalles",
  "label_startingRoute": "Ruta inicial:",
  "label_startingRouteDescription": "Esto cambiará permanentemente el estado de la ruta. ¿Quieres continuar?",
  "label_totalTasks": "Tareas totales:",
  "label_time": "Tiempo:",
  "txt_timeMin": "{time} min",
  "label_distance": "Distancia:",
  "txt_distanceKm": "{distance} km",
  "label_taskID": "ID de tarea:",
  "label_reportIncident": "Incidente de informe",
  "label_selectCategory": "Selecciona una categoría",
  "label_selectSubCategory": "Seleccionar subcategoría",
  "label_selectedCategory": "Categoría seleccionada",
  "label_moreDetails": "Más detalles",
  "label_addPhoto": "Añadir foto",
  "label_addSomePhoto": "Por favor agregue la foto",
  "label_addNote": "Añadir la nota",
  "label_addSomeNote": "Agregue nota",
  "label_addMedia": "Agregar medios",
  "alert_incidentAddedSuccessfully": "¡Incidente reportado con éxito!",
  "alert_observationAddedSuccessfully": "¡Observación reportada con éxito!",
  "menu_observation": "Agregar observación",
  "btn_submit": "Entregar",
  "label_camera": "Cámara",
  "label_gallery": "Galería",
  "alert_pleaseAddMedia": "Por favor, agregue el archivo multimedia",
  "alert_selectOneCategory": "Seleccione una categoría",
  "alert_selectOneSubCategory": "Seleccione una subcategoría",
  "alert_startOneRouteBeforeCanTakeAnyAction": "Debe comenzar una ruta antes que pueda continuar con esta acción.",
  "txt_observationSentFail": "Su observación no pudo enviar, por favor intente de nuevo",
  "label_reportObservation": "Observación de informes",
  "label_breakTime": "Descanso",
  "label_breakDescription": "Puede comenzar el descanso cuando desee descansar, se contará desde su descanso total hasta que lo detenga.",
  "label_remainingTime": "Restante",
  "button_startBreak": "Tomar un descanso",
  "button_endBreak": "Descanso final",
  "menu_addCrew": "Gestionar la tripulación",
  "err_clientNotForEnvironment": "Su cliente no está registrado para {baseUrl}",
  "hint_corporateKey": "Clave corporativa",
  "btn_register": "Registro",
  "txt_task": "Tarea",
  "label_attachment": "Adjunto",
  "label_overview": "Descripción general",
  "txt_noAttachmentFound": "No se encontró un archivo adjunto",
  "title_postRouteQuestions": "Preguntas posteriores a la ruta",
  "label_odometerReading": "Lectura de hora",
  "label_enterOdometerInfo": "Ingrese la información de HourMeter",
  "label_kilometerReading": "Lectura de kilómetro",
  "label_enterKilometerInfo": "Ingrese la información del kilómetro",
  "label_preVehicleReadingQuestions": "Preguntas de lectura previa al vehículo",
  "label_preQhseQuestions": "Preguntas previas a QHSE",
  "label_postVehicleReadingQuestions": "Preguntas de lectura de vehículos",
  "label_postQhseQuestions": "Publicar preguntas QHSE",
  "btn_retry": "Rever",
  "label_createNewTask": "Crear una nueva tarea",
  "label_newTask": "Nueva tarea",
  "label_searchByIdOrName": "Buscar por identificación o nombre",
  "label_useCurrentLocation": "Utilice la ubicación actual",
  "label_selectLocation": "Seleccionar ubicación",
  "label_whereDoYouWantToCreateYourTask": "¿Dónde quieres crear tu tarea?",
  "label_servicePointsNotFound": "Puntos de servicio no encontrados",
  "label_noServicePointFoundNearYouPleaseSearchUsingThe": "No se encuentra ningún punto de servicio cerca de usted, busque el cuadro de búsqueda.",
  "label_servicePointsLoading": "Carga de puntos de servicio",
  "label_loadingServicePointsNearYouPleaseWait": "Cargando puntos de servicio cerca de usted, espere ...",
  "label_estimatedMeter": "{meter} m estimado",
  "label_currentLocation": "Ubicación actual",
  "label_selectTaskTemplate": "Seleccionar plantilla de tareas",
  "label_chooseTemplateForTask": "Elija la plantilla para la tarea",
  "label_pleaseSelectTaskTemplate": "Seleccione la plantilla de tareas",
  "label_taskCreatedSuccessfully": "¡Tarea creada con éxito!",
  "label_menu": "Menú",
  "label_logout": "Cerrar sesión",
  "label_areYouSure": "¿Está seguro?",
  "label_yourSessionWillExpireAreYouSure": "Su sesión caducará, ¿estás seguro?",
  "label_settings": "Ajustes",
  "label_technicalSupport": "Apoyo técnico",
  "label_legalConsiderations": "Consideraciones legales",
  "returnToMainRoute": "Volver a la ruta principal",
  "label_aboutUs": "Sobre nosotros",
  "label_assets": "Activos",
  "menu_loadAsset": "Administrar activos",
  "label_addManually": "Agregar manualmente",
  "label_addByScanQrCode": "Escanear código QR",
  "label_addByRFID": "Lectura rfid",
  "label_inVehicleAsset": "Activos en la ruta",
  "label_attachedAssets": "Activos adjuntos",
  "alert_noAssetTitle": "No adjunto",
  "alert_noAssetDesc": "Desafortunadamente, no hay activos adjuntos.",
  "btn_select": "Seleccionar",
  "label_searchForAsset": "Buscar activos",
  "label_searchForAssetDescription": "Busque el activo que desea agregar",
  "label_searchForAssetHint": "Ingrese el código de activo, el nombre o la identificación",
  "alert_deleteAssetDesc": "{assetTag} será eliminado, ¿confirma?",
  "label_searchForAssetByRFID": "Los activos cercanos a usted se agregarán automáticamente",
  "button_delete": "Borrar",
  "alert_endRouteAlert": "Una vez que termine la ruta, no podrá deshacer la acción. ¿Quieres continuar?",
  "alert_routeNotCompleteYetTitleAlert": "La ruta aún no se ha completado, ¿estás seguro?",
  "alert_routeNotCompleteYetDescAlert": "Todavía no ha completado todas las tareas, ¿está seguro de que desea finalizar la ruta? Esta acción no se puede deshacer.",
  "alert_detachAllAssetTitleAlert": "Necesitas separar los activos",
  "alert_detachAllAssetDescAlert": "Al final de la ruta, debe separar todos los activos.",
  "btn_detachAll": "Separar todo",
  "label_routeSummary": "Resumen de ruta",
  "label_congrats": "¡Felicidades!",
  "label_routeSummaryMsg": "Su ruta ha terminado. Su resumen de ruta es el siguiente;",
  "label_totalDuration": "Duración total",
  "label_taskCompleted": "Tarea terminada",
  "label_fuelTaken": "Combustible tomado",
  "label_totalDisposal": "Eliminación total",
  "btn_addMore": "Añadir más",
  "txt_routeSummaryTotalTime": "{hrs} hrs a2 min",
  "txt_routeSummaryBreakTime": "{mins} min",
  "txt_routeSummaryFuel": "{fuel} LT",
  "txt_routeSummaryDisposal": "{fuel} kg",
  "alert_finishRouteDetachError": "El proceso de separación de todos los activos no se ha completado, intente nuevamente antes de finalizar su ruta.",
  "guided_depart": "Salir",
  "guided_arrive": "Llegar",
  "guided_leftUTurn": "Izquierda en u girado",
  "guided_sharpLeftTurn": "Giro a la izquierda afilada",
  "guided_leftTurn": "Giro a la izquierda",
  "guided_slightLeftTurn": "Leve giro a la izquierda",
  "guided_continue": "Continuar",
  "guided_slightRightTurn": "Ligero giro a la derecha",
  "guided_rightTurn": "Vuelta a la derecha",
  "guided_sharpRightTurn": "Giro a la derecha afilada",
  "guided_rightUTurn": "Giro en U",
  "guided_leftExit": "Salida izquierda",
  "guided_rightExit": "Salida correcta",
  "guided_leftRamp": "Rampa izquierda",
  "guided_rightRamp": "Rampa correcta",
  "guided_leftFork": "Horcor izquierdo",
  "guided_middleFork": "Tenedor de bifurcación",
  "guided_rightFork": "Tenedor derecho",
  "guided_ferry": "Transportar",
  "guided_leftRoundaboutEnter": "Roundabout de izquierda Enter",
  "guided_rightRoundaboutEnter": "RoundAbout de la derecha Enter",
  "guided_leftRoundaboutPass": "Pase de rotonda izquierda",
  "guided_rightRoundaboutPass": "Pase de rotonda derecha",
  "guided_leftRoundaboutExit1": "RoundAbout de izquierda Salida 1",
  "guided_leftRoundaboutExit2": "RoundAbout de izquierda Salida 2",
  "guided_leftRoundaboutExit3": "Roundación de izquierda Exit 3",
  "guided_leftRoundaboutExit4": "RoundAbout de izquierda Salida 4",
  "guided_leftRoundaboutExit5": "RoundAbout de izquierda Salida 5",
  "guided_leftRoundaboutExit6": "RoundAbout de izquierda Salida 6",
  "guided_leftRoundaboutExit7": "RoundAbout de izquierda Salida 7",
  "guided_leftRoundaboutExit8": "RoundAbout de izquierda Salida 8",
  "guided_leftRoundaboutExit9": "RoundAbout de izquierda Salida 9",
  "guided_leftRoundaboutExit10": "RoundAbout de izquierda Salida 10",
  "guided_leftRoundaboutExit11": "RoundAbout de izquierda Salida 11",
  "guided_leftRoundaboutExit12": "RoundAbout de izquierda Salida 12",
  "guided_rightRoundaboutExit1": "RoundAbout de la derecha Salida 1",
  "guided_rightRoundaboutExit2": "RoundAbout de la derecha Salida 2",
  "guided_rightRoundaboutExit3": "RoundAbout de la derecha Exit 3",
  "guided_rightRoundaboutExit4": "RoundAbout de la derecha Salida 4",
  "guided_rightRoundaboutExit5": "RoundAbout de la derecha Salida 5",
  "guided_rightRoundaboutExit6": "RoundAbout de la derecha Salida 6",
  "guided_rightRoundaboutExit7": "RoundAbout de la derecha Salida 7",
  "guided_rightRoundaboutExit8": "RoundAbout de la derecha Salida 8",
  "guided_rightRoundaboutExit9": "RoundAbout de la derecha Salida 9",
  "guided_rightRoundaboutExit10": "RoundAbout de la derecha Salida 10",
  "guided_rightRoundaboutExit11": "RoundAbout de la derecha Salida 11",
  "guided_rightRoundaboutExit12": "RoundAbout de la derecha Salida 12",
  "label_signatureSubTitle": "Firme dentro del área forrada para su aprobación",
  "btn_clear": "Claro",
  "label_signHere": "Firma aqui",
  "btn_selectAsset": "Seleccionar activo",
  "btn_addMedia": "Agregar medios",
  "btn_addItem": "Añadir artículo",
  "title_changeTaskStatus": "Cambiar el estado de la tarea",
  "txt_selectStatus": "Seleccionar estado",
  "txt_selectStatusOfTheTask": "Seleccione el nuevo estado de la tarea",
  "title_addItem": "Añadir artículo",
  "txt_selectedItem": "Item seleccionado",
  "title_itemValues": "Valores de elementos",
  "txt_fillRequiredFields": "Complete los campos requeridos",
  "toast_fillRequiredFields": "por favor llene todos los campos requeridos",
  "txt_quantityPcs": "PCS {quantity}",
  "label_quantity": "Cantidad",
  "err_pleaseSelectItemFirst": "Seleccione el artículo primero",
  "txt_plannedQuantity": "Planeado: PCS {quantity}",
  "txt_plannedAmount": "Planeado: {amount} {uom}",
  "title_selectItem": "Seleccione un artículo",
  "label_addFuel": "Agregue combustible",
  "label_select": "Seleccionar",
  "label_selectFuelPoint": "Seleccionar punto de combustible",
  "label_searchByName": "Buscar por nombre",
  "label_fuelPointsNotFound": "Puntos de combustible no encontrados",
  "label_fuelPoint": "Punto de combustible",
  "label_pleaseSelectFuelPoint": "Seleccione el punto de combustible",
  "label_step": "Paso {stepNumber}",
  "label_estimatedKiloMeter": "{kilometer} km estimado",
  "label_pleaseAddFuelAmount": "Agregue la cantidad de combustible",
  "label_liter": "Teniente",
  "label_fuelAddedSuccessfully": "¡Combustible agregado con éxito!",
  "label_fuelInformationCouldNotBeSent": "No se pudo enviar información de combustible.",
  "btn_view": "Vista",
  "btn_decline": "Rechazar",
  "btn_accept": "Aceptar",
  "btn_cancel": "Cancelar",
  "label_youWillNotBeAbleToLoginWithoutAcceptingAre": "No podrás iniciar sesión sin aceptar, ¿estás seguro?",
  "label_addDisposal": "Agregar disposición",
  "label_disposalPoint": "Punto de eliminación",
  "label_pleaseSelectDisposalPoint": "Seleccione el punto de eliminación",
  "label_selectDisposalPoint": "Seleccionar punto de eliminación",
  "label_disposalPointsNotFound": "Puntos de combustible no encontrados",
  "label_pleaseAddDisposalAmount": "Agregue el monto de la eliminación",
  "label_kilogram": "KG",
  "label_disposalAddedSuccessfully": "¡La eliminación se agregó con éxito!",
  "label_disposalInformationCouldNotBeSent": "No se pudo enviar información de eliminación.",
  "label_assetsOnTransition": "Activos en transición",
  "txt_mandatory": "Obligatorio",
  "txt_amountUom": "{amount} {uom}",
  "tab_listView": "Vista de la lista",
  "tab_mapView": "Vista del mapa",
  "label_tasksNotFound": "Tareas no encontradas",
  "label_noTasksFound": "No se encontraron tareas",
  "offlineTransitionSave": "Debido al error de red, su transición guardada para enviar más tarde",
  "err_taskSyncIssue": "Su tarea no está sincronizada con el servidor, este incidente está registrado, por favor comuníquese con su administrador",
  "txt_noAssetFoundYet": "No se encontró ningún activo todavía",
  "err_noZebraPrinter": "¡No se encuentra la impresora Zebra para los detalles de impresión!",
  "toast_corporateSuccess": "¡Clave corporativa cambió con éxito!",
  "err_youMustIgnoreBatteryOptimizationsForBackgroundProcess": "Debe ignorar las optimizaciones de la batería para el proceso de fondo.",
  "label_internetConnectionIsRequiredToAccessTheServerPleaseMake": "Se requiere conexión a Internet para acceder al servidor. Asegúrese de tener acceso a Internet.",
  "label_jailbreakDetected": "Jailbreak detectado",
  "label_yourDeviceHasBeenJailbrokenFieldWorkDoesNotWork": "Su dispositivo ha sido Jailbreak. El trabajo de campo no funciona en dispositivos Jailbreak. Elimine el jailbreak y restablezca su dispositivo para usar la aplicación.",
  "title_newTasks": "Tienes nuevas tareas",
  "txt_newTasks": "{count} nuevas tareas están disponibles para su ruta, su lista de tareas se actualizará automáticamente.",
  "btn_close": "Cerca",
  "btn_showNewTasks": "Mostrar nuevas tareas",
  "txt_transitionAppliedSuccessfully": "Transición aplicada con éxito",
  "label_version": "Versión {versionInfo}",
  "err_noTaskForScan": "No hay tarea disponible para su escaneo",
  "label_availableAssetDataCouldntFetched": "Los datos de activos disponibles no pudieron obtener, comuníquese con el administrador",
  "label_crewOnRoute": "Tripulación en ruta",
  "label_selectCrew": "Seleccionar tripulación",
  "label_enterCrewDriverIdOrUsername": "Seleccione la tripulación ingresando la identificación del conductor o el nombre de usuario",
  "label_vehicleCrew": "Tripulación de vehículos",
  "label_crewsAddedToVehicle": "Cuerpos agregados al vehículo",
  "btn_addCrew": "Agregar tripulación",
  "label_noCrew": "No tripulando",
  "label_sorryNoCrew": "Lo siento, no hay tripulación.",
  "label_enterDriverIdOrUsername": "Ingrese la identificación del conductor o el nombre de usuario",
  "label_enterAssetName": "Ingrese el nombre del activo",
  "err_assetIdCouldNotBeConverted": "La identificación del activo no se pudo convertir",
  "label_assetsSearching": "Búsqueda de activos ...",
  "label_pleaseWait": "Espere por favor...",
  "label_addCrew": "Agregar tripulación",
  "label_crewAddedRouteSuccess": "La tripulación se agregó a la ruta con éxito",
  "label_crewRemovedRouteSuccess": "La tripulación fue retirada de la ruta con éxito",
  "label_crewIsBeingSearched": "La tripulación está siendo registrada ...",
  "label_noCrewFound": "No se encontró ningún equipo",
  "label_searchForTheCrewYouWantToAdd": "Busque la tripulación que desea agregar",
  "label_searchForACrew": "Buscar una tripulación",
  "label_noAsset": "Sin activo",
  "label_items": "Elementos",
  "label_noAssets": "Sin activos",
  "label_addedAssetsWillAppearHere": "Los activos agregados aparecerán aquí",
  "label_noItems": "No hay artículos",
  "label_addedItemsWillAppearHere": "Los artículos agregados aparecerán aquí",
  "err_noDascomDeviceFound": "No se encuentra la impresora de etiqueta Dascom, asegúrese de que la impresora de etiqueta conectada y unida con el dispositivo",
  "err_weCouldntRefreshYourInroute": "Debido a un error de red, no pudimos actualizar sus activos en el ruta",
  "label_recentDisposals": "Disposiciones recientes",
  "label_noDisposal": "Sin disposición",
  "label_addedDisposalsWillAppearHere": "Las disposiciones agregadas aparecerán aquí.",
  "label_recentFuels": "Combustibles recientes",
  "label_noFuels": "Sin combustibles",
  "label_addedFuelsWillAppearHere": "Los combustibles agregados aparecerán aquí.",
  "label_location": "Ubicación",
  "err_notCloseEnough": "No está lo suficientemente cerca como para aplicar la transición para esta tarea",
  "label_dropAssetNotLoaded": "No cargó el activo requerido para esta tarea. Por favor cargue los activos.",
  "label_pickAssetNotLoaded": "No hay un activo disponible en este punto de servicio para recolectar, comuníquese con su administrador.",
  "label_assetNotLoaded": "Activo no cargado",
  "btn_manageAssets": "Administrar activos",
  "label_options": "Opción",
  "btn_editItem": "Elemento de edición",
  "btn_removeItem": "Remover el artículo",
  "label_itemWillBeDeletedDoYouConfirm": "{item} será eliminado, ¿confirma?",
  "label_item": "Artículo",
  "btn_delete": "Borrar",
  "err_unsecuredNetwork": "Red no garantizada",
  "txt_unsecureNetworkDetected": "Detectamos que la aplicación no se ejecuta en la red no segura \n, consulte su conexión de red o contacte con el administrador",
  "err_dueToANetworkErrorWeCouldntRefresh": "Debido a un error de red, no pudimos actualizar su distancia y duración de la ruta total.",
  "label_pleaseSelectFromList": "Seleccione una de las transiciones de la lista",
  "label_batteryLevelIsCritical": "El nivel de la batería es crítico",
  "label_batteryLevelIsCriticallyLowPleaseCharge": "El nivel de la batería es críticamente bajo, ¡cargue!",
  "btn_ok": "De acuerdo",
  "label_noAvailableAsset": "No hay activo disponible",
  "btn_goToSettings": "Ir a la configuración",
  "label_pleaseEnableLocationAlwaysPermissionFromSettings": "Habilite la ubicación siempre permiso desde la configuración",
  "label_locationPermissionDenied": "Permiso de ubicación denegado",
  "label_appTrackingDesc": "Para que las funciones de aplicación funcionen correctamente, necesitamos usar sus datos de ubicación en segundo plano, por lo que podrá beneficiarse de las capacidades de aplicación basadas en la ubicación. Permita el permiso de seguimiento de aplicaciones.",
  "title_waitingAppTrackingPermission": "Permiso de seguimiento de aplicaciones de espera",
  "label_needAppTracking": "Debe permitir que el seguimiento de aplicaciones continúe operando",
  "err_requiredItemFill": "Llene todos los artículos en la página",
  "txt_selectedAsset": "Activo seleccionado",
  "txt_pcs": "pcs",
  "label_showGuidedNavigation": "Mostrar navegación guiada",
  "btn_getDirections": "Obtener Las Direcciones",
  "label_navigationWillBeDisplayedFor": "La navegación se mostrará para la tarea que seleccionó, ¿está seguro?",
  "label_youNeedToLoadAssets": "Necesitas cargar activos",
  "label_thereAreTasksThatRequireAsset": "Hay tareas que requieren carga de activos. No olvides cargar antes de comenzar la ruta",
  "btn_load": "Carga",
  "err_thisAssetIsNotInRoute": "Este activo no está en ruta.",
  "label_transitionInProgress": "Transición en progreso",
  "label_pickAndDropSuccessful": "El activo {pickAsset} eligió y el activo {dropAsset} cayó con éxito.",
  "label_transitionFailed": "La transición falló.",
  "button_retry": "Rever",
  "title_pickAndDropAction": "Acción de seleccionar y soltar",
  "err_thereAreMandatoryFieldsInTransition": "Hay campos obligatorios sin rellenar en su flujo de trabajo",
  "err_dropAssetFetchingFailed": "Falló",
  "txt_tabToContinuePickAndDrop": "Tab Tab Continúe seleccionando el activo descartado.",
  "txt_youArePickingAsset": "Estás eligiendo Asset {assetName} para la siguiente tarea:",
  "btn_continue": "Continuar",
  "title_pickingAsset": "Recolección de activo",
  "err_inVehicleStatusChangeErr": "Falló en cambiar el estado del activo a dentro del vehículo",
  "err_pickOrDropMissing": "El activo de seleccionar o soltar no se encuentra en los pasos de transición",
  "err_pickTagNotDropTag": "La etiqueta de activo de selección y solta no puede ser la misma",
  "btn_offlineSaved": "Fuera de línea guardado",
  "err_alreadyInSP": "Este activo ya está en el punto de servicio",
  "err_thereIsNoAssetFound": "No se encuentra ningún activo para este escaneo",
  "err_noSpForAsset": "Este activo no pertenece a ningún punto de servicio",
  "err_servicePointFetchingFailed": "Punto de servicio Falling Falling",
  "err_taskCreationFailed": "La creación de tareas falló para este escaneo",
  "err_taskCouldntAssigned": "La tarea creada no se pudo asignar la ruta actual",
  "err_noTransitionForTask": "La tarea encontrada no tiene transición de ajuste disponible para Pick & Drop",
  "err_thisAssetNotAvailable": "Este activo no está disponible para esta tarea.",
  "txt_actualW": "Peso",
  "err_taskCreateFailed": "La creación de tareas falló para la etiqueta escaneada de activos: {data}",
  "err_failedTransitionSelect": "Falló al elegir la transición para {targetState}, para la tarea {taskId}",
  "label_pleaseEnableLocation": "El servicio de ubicación está deshabilitado. Por favor, habilítelo para usar la aplicación.",
  "err_requestTimeout": "Tiempo de solicitud agotado, por favor intente nuevamente más tarde",
  "err_locationIsNotAvailable": "Ubicación no disponible",
  "label_goalReached": "Meta alcanzada",
  "label_aRouteToTheNewMissionWillBeCreatedWithin": "Una ruta para la nueva misión se creará en {seconds} segundos",
  "label_noTaskFoundInTheQueue": "No se encontró ninguna tarea en la cola",
  "label_creatingARouteToTheNextMission": "Creando una ruta para la próxima misión.",
  "label_pleaseSelectALocationOrServicePointToCreateA": "Por favor seleccione una ubicación o punto de servicio para crear una tarea.",
  "label_loading": "Cargando",
  "label_anyItemIsNotFound": "No se encontró ningún elemento.",
  "btn_create": "Crear",
  "err_thereIsNoDefinedShortcutForThisOperation": "No hay un atajo definido para esta operación",
  "err_scannedAssetIsNotInOurSystem": "El activo escaneado no está en nuestro sistema. Por favor, contacte con su supervisor o use la aplicación móvil E360 para registrarlo.",
  "err_scannedAssetTypeIsNotMatched": "El tipo de activo escaneado no coincide con los datos de configuración de la acción de atajo",
  "err_scannedAssetIsNotLinkedWithSP": "El activo escaneado no está vinculado con el Punto de Servicio. Contacte a su supervisor o use la aplicación móvil E360 para adjuntar el activo.",
  "err_operationIsNotSelected": "No se ha seleccionado una operación",
  "err_fetchedTaskTemplatesAreEmpty": "Las plantillas de tareas obtenidas están vacías",
  "err_fetchedTaskTemplatesAreNotMatched": "Las plantillas de tareas obtenidas no coinciden con los datos de acción",
  "err_taskTemplatesFetchingFailed": "Error al obtener las plantillas de tareas",
  "err_taskCreationHasFailed": "La creación de la tarea ha fallado",
  "err_taskIsNotInTheCorrectState": "La tarea no está en el estado correcto",
  "err_thereIsNoTargetTransitionAmongTheTasksTransitions": "No hay una transición de destino entre las transiciones de la tarea.",
  "err_pickAssetFetchingFailedScannedTagData": "Error al obtener el activo recogido, etiqueta escaneada: {data}",
  "err_pickOrCollectAssetNotFoundInTransitionSteps": "No se encontró el activo para recoger o recolectar en los pasos de transición",
  "err_vcrFormSendFailed": "Error al enviar el formulario VCR",
  "err_noRouteSelected": "No se ha seleccionado una ruta",
  "btn_support": "Soporte",
  "btn_unSupport": "Cancelar soporte",
  "btn_save": "Ahorrar",
  "label_attachmentSaved": "Archivo adjunto guardado",
  "label_attachmentSaveError": "No se pudo guardar el archivo adjunto",
  "btn_download": "Descargar",
  "label_notRobot": "No soy un robot",
  "label_servicePointMedias": "Puntos de Servicio Medios",
  "btn_printQR": "Imprimir QR",
  "btn_update": "Actualizar",
  "err_failedToPrint": "Falló, por favor intente nuevamente o contacte con el soporte",
  "label_print": "Imprimir",
  "label_disconnected": "Desconectado",
  "label_connected": "Conectado",
  "label_connecting": "Conectando...",
  "label_printing": "Imprimiendo...",
  "label_locationIsNotAvailablePleaseTryAgain": "Ubicación no disponible, por favor intente nuevamente",
  "err_editingDisabledThisField": "No puede editar este campo",
  "err_editPermissionDenied": "No tiene permiso para editar",
  "title_editTransition": "Editar transición",
  "title_takeAction": "Realizar acción",
  "err_noDriverPermission": "No tiene permiso de conductor",
  "err_errorOccuredPleaseLoginAgain": "Ocurrió un error, por favor inicie sesión nuevamente",
  "label_enterOneTimePassword": "Ingrese una contraseña de uso único",
  "btn_submitCode": "Enviar código",
  "label_enterCode": "Ingrese el código de su aplicación Authenticator.",
  "err_invalidMFAValue": "Valor MFA inválido!",
  "toast_pleaseEnterTheOTP": "Por favor ingrese el OTP",
  "toast_invalidMFAType": "Tipo MFA inválido",
  "toast_userNotFound": "Usuario no encontrado",
  "toast_undefinedMFAType": "Tipo MFA indefinido",
  "toast_mfaAlreadyActivated": "MFA ya activado",
  "toast_invalidMFAValue": "Valor MFA inválido",
  "toast_invalidMFAState": "Estado MFA inválido",
  "tab_media": "Medios",
  "label_transitionMedias": "Transiciones Medios",
  "label_taskMedias": "Tareas Medios",
  "label_pleaseAllowLocation": "Por favor, permita el permiso de ubicación para continuar",
  "err_unableToStartEnvironmentService": "El servicio de entorno no se pudo inicializar. Por favor, inténtelo de nuevo.",
  "label_currentLocationNotAvailable": "La ubicación actual no está disponible, por favor, inténtelo más tarde.",
  "err_serverError": "Ocurrió un error en el servidor. Por favor, inténtelo más tarde."
}
